instruct_goose/__init__.py
instruct_goose/_modidx.py
instruct_goose/agent.py
instruct_goose/core.py
instruct_goose/dataset.py
instruct_goose/env.py
instruct_goose/reward.py
instruct_goose/trainer.py
instruct_goose/utils.py
instruct_goose-0.0.7.dist-info/LICENSE
instruct_goose-0.0.7.dist-info/METADATA
instruct_goose-0.0.7.dist-info/WHEEL
instruct_goose-0.0.7.dist-info/entry_points.txt
instruct_goose-0.0.7.dist-info/top_level.txt
instruct_goose-0.0.7.dist-info/RECORD
