Metadata-Version: 2.1
Name: instruct-goose
Version: 0.0.7
Summary: Implementation of Reinforcement Learning from Human Feedback (RLHF)
Home-page: https://github.com/xrsrke/instructGOOSE
Author: xrsrke
Author-email: xariusdrake@hotmail.com
License: Apache Software License 2.0
Keywords: rlhf reinforcement-learning human-feedback chatgpt instructgpt
Classifier: Development Status :: 4 - Beta
Classifier: Intended Audience :: Developers
Classifier: Natural Language :: English
Classifier: Programming Language :: Python :: 3.7
Classifier: Programming Language :: Python :: 3.8
Classifier: Programming Language :: Python :: 3.9
Classifier: Programming Language :: Python :: 3.10
Classifier: License :: OSI Approved :: Apache Software License
Requires-Python: >=3.7
License-File: LICENSE
Requires-Dist: transformers
Requires-Dist: datasets
Requires-Dist: wandb
Requires-Dist: pandas
Requires-Dist: gymnasium
Requires-Dist: pyyaml
Requires-Dist: pytest
Requires-Dist: tqdm
Requires-Dist: python-dotenv
Requires-Dist: einops
Requires-Dist: torch
Requires-Dist: pytorch-lightning
Requires-Dist: torchtyping
Requires-Dist: ray
Provides-Extra: dev
